node_graph_widget/__init__.py
node_graph_widget/html_template.py
node_graph_widget/utils.py
node_graph_widget/static/widget.css
node_graph_widget/static/widget.js
node_graph_widget-0.0.5.dist-info/METADATA
node_graph_widget-0.0.5.dist-info/WHEEL
node_graph_widget-0.0.5.dist-info/licenses/LICENSE
node_graph_widget-0.0.5.dist-info/RECORD
